{
    "configurations": [
        {
            "name": "Win32",
            "includePath": [
                "C:\\Users\\Scott\\AppData\\Local\\Arduino15\\packages\\esp32\\tools\\**",
                "C:\\Users\\Scott\\AppData\\Local\\Arduino15\\packages\\esp32\\hardware\\esp32\\1.0.2\\**",
                "C:\\Users\\Scott\\AppData\\Local\\Arduino15\\packages\\esp8266\\tools\\**",
                "C:\\Users\\Scott\\AppData\\Local\\Arduino15\\packages\\esp8266\\hardware\\esp8266\\2.5.2\\**",
                "C:\\Program Files (x86)\\Arduino\\tools\\**",
                "C:\\Program Files (x86)\\Arduino\\hardware\\arduino\\avr\\**"
            ],
            "forcedInclude": [],
            "intelliSenseMode": "msvc-x64",
            "compilerPath": "C:/Program Files (x86)/Microsoft Visual Studio/2017/Professional/VC/Tools/MSVC/14.14.26428/bin/Hostx64/x64/cl.exe",
            "cStandard": "c11",
            "cppStandard": "c++17"
        }
    ],
    "version": 4
}